Metadata-Version: 2.3
Name: litestar-tailwind-cli
Version: 0.2.0
Summary: Provides a CLI plugin for Litestar to use Tailwind CSS via the Tailwind CLI.
Project-URL: Documentation, https://github.com/Tobi-De/litestar-tailwind-cli#readme
Project-URL: Issues, https://github.com/Tobi-De/litestar-tailwind-cli/issues
Project-URL: Source, https://github.com/Tobi-De/litestar-tailwind-cli
Author-email: Tobi DEGNON <tobidegnon@proton.me>
License-Expression: MIT
License-File: LICENSE.txt
Keywords: litestar,tailwindcss
Classifier: Development Status :: 4 - Beta
Classifier: Intended Audience :: Developers
Classifier: Programming Language :: Python
Classifier: Programming Language :: Python :: 3 :: Only
Classifier: Programming Language :: Python :: 3.8
Classifier: Programming Language :: Python :: 3.9
Classifier: Programming Language :: Python :: 3.10
Classifier: Programming Language :: Python :: 3.11
Classifier: Programming Language :: Python :: 3.12
Classifier: Programming Language :: Python :: Implementation :: CPython
Classifier: Programming Language :: Python :: Implementation :: PyPy
Classifier: Topic :: Software Development
Classifier: Typing :: Typed
Requires-Python: >=3.8
Requires-Dist: litestar[standard]
